{
  "frames": [
    {
      "name": "sprite-01",
      "position": {
        "x": 0,
        "y": 0,
        "w": 32,
        "h": 40
      }
    },
    {
      "name": "sprite-02",
      "position": {
        "x": 32,
        "y": 0,
        "w": 32,
        "h": 40
      }
    },
    {
      "name": "sprite-03",
      "position": {
        "x": 64,
        "y": 0,
        "w": 32,
        "h": 40
      }
    },
    {
      "name": "sprite-04",
      "position": {
        "x": 96,
        "y": 0,
        "w": 32,
        "h": 40
      }
    },
    {
      "name": "sprite-05",
      "position": {
        "x": 128,
        "y": 0,
        "w": 32,
        "h": 40
      }
    },
    {
      "name": "sprite-06",
      "position": {
        "x": 160,
        "y": 0,
        "w": 32,
        "h": 40
      }
    },
    {
      "name": "sprite-07",
      "position": {
        "x": 192,
        "y": 0,
        "w": 32,
        "h": 40
      }
    },
    {
      "name": "sprite-08",
      "position": {
        "x": 224,
        "y": 0,
        "w": 32,
        "h": 40
      }
    },
    {
      "name": "sprite-01",
      "position": {
        "x": 0,
        "y": 32,
        "w": 32,
        "h": 40
      }
    },
    {
      "name": "sprite-02",
      "position": {
        "x": 32,
        "y": 32,
        "w": 32,
        "h": 40
      }
    },
    {
      "name": "sprite-03",
      "position": {
        "x": 64,
        "y": 32,
        "w": 32,
        "h": 40
      }
    },
    {
      "name": "sprite-04",
      "position": {
        "x": 96,
        "y": 32,
        "w": 32,
        "h": 40
      }
    },
    {
      "name": "sprite-05",
      "position": {
        "x": 128,
        "y": 32,
        "w": 32,
        "h": 40
      }
    },
    {
      "name": "sprite-06",
      "position": {
        "x": 160,
        "y": 32,
        "w": 32,
        "h": 40
      }
    },
    {
      "name": "sprite-07",
      "position": {
        "x": 192,
        "y": 32,
        "w": 32,
        "h": 40
      }
    },
    {
      "name": "sprite-08",
      "position": {
        "x": 224,
        "y": 32,
        "w": 32,
        "h": 40
      }
    },
    {
      "name": "sprite-01",
      "position": {
        "x": 0,
        "y": 64,
        "w": 32,
        "h": 40
      }
    },
    {
      "name": "sprite-02",
      "position": {
        "x": 32,
        "y": 64,
        "w": 32,
        "h": 40
      }
    },
    {
      "name": "sprite-03",
      "position": {
        "x": 64,
        "y": 64,
        "w": 32,
        "h": 40
      }
    },
    {
      "name": "sprite-04",
      "position": {
        "x": 96,
        "y": 64,
        "w": 32,
        "h": 40
      }
    }
  ]
}
